crypto_pkg/__init__.py
crypto_pkg/entry_point.py
crypto_pkg/number_operations.py
crypto_pkg/settings.py
crypto_pkg/attacks/__init__.py
crypto_pkg/attacks/block_ciphers/__init__.py
crypto_pkg/attacks/block_ciphers/double_encryption.py
crypto_pkg/attacks/block_ciphers/modified_aes.py
crypto_pkg/attacks/block_ciphers/utils.py
crypto_pkg/attacks/power_analysis/__init__.py
crypto_pkg/attacks/power_analysis/correlation_power_analysis.py
crypto_pkg/attacks/power_analysis/test_file.pickle
crypto_pkg/attacks/stream_ciphers/__init__.py
crypto_pkg/attacks/stream_ciphers/geffe_cipher.py
crypto_pkg/ciphers/__init__.py
crypto_pkg/ciphers/asymmetric/__init__.py
crypto_pkg/ciphers/asymmetric/DGHV/__init__.py
crypto_pkg/ciphers/asymmetric/DGHV/dghv.py
crypto_pkg/ciphers/asymmetric/rsa/__init__.py
crypto_pkg/ciphers/asymmetric/rsa/rsa_scheme.py
crypto_pkg/ciphers/symmetric/__init__.py
crypto_pkg/ciphers/symmetric/aes.py
crypto_pkg/ciphers/symmetric/geffe.py
crypto_pkg/clis/__init__.py
crypto_pkg/clis/attacks.py
crypto_pkg/clis/cli.py
crypto_pkg/contracts/__init__.py
crypto_pkg/contracts/cli_dto.py
crypto_pkg/contracts/exceptions.py
crypto_pkg/contracts/prime_numbers.py
crypto_pkg/contracts/rsa_scheme.py
crypto_pkg/number_theory/__init__.py
crypto_pkg/number_theory/number_theory.py
crypto_pkg/number_theory/prime_numbers.py
crypto_pkg/utils/__init__.py
crypto_pkg/utils/logging.py
crypto_pkg-1.6.2.dist-info/LICENSE
crypto_pkg-1.6.2.dist-info/METADATA
crypto_pkg-1.6.2.dist-info/WHEEL
crypto_pkg-1.6.2.dist-info/entry_points.txt
crypto_pkg-1.6.2.dist-info/top_level.txt
crypto_pkg-1.6.2.dist-info/zip-safe
crypto_pkg-1.6.2.dist-info/RECORD
