Metadata-Version: 2.1
Name: crypto_pkg
Version: 1.6.2
Summary: A cryptoanalysis package
Home-page: https://github.com/programmingAthlete/crypto_pkg.git
Author: programmingAthlete
Author-email: luca.bonamino@hotmail.com
Classifier: Programming Language :: Python :: 3
Classifier: License :: OSI Approved :: MIT License
Classifier: Operating System :: OS Independent
License-File: LICENSE
Requires-Dist: pycryptodome >=3.19.0
Requires-Dist: typer[all]
Requires-Dist: pydantic <2,>=1.8
Requires-Dist: numpy >=1.24.2
Requires-Dist: matplotlib >=3.7.1
